YafYonghushouce/README.md
YafYonghushouce/__init__.py
YafYonghushouce/__main__.py
YafYonghushouce/file.epub
YafYonghushouce/index.html
YafYonghushouce/css/__init__.py
YafYonghushouce/css/annotations.css
YafYonghushouce/css/main.css
YafYonghushouce/css/normalize.css
YafYonghushouce/css/popup.css
YafYonghushouce/font/__init__.py
YafYonghushouce/font/fontello.eot
YafYonghushouce/font/fontello.svg
YafYonghushouce/font/fontello.ttf
YafYonghushouce/font/fontello.woff
YafYonghushouce/img/__init__.py
YafYonghushouce/img/annotator-glyph-sprite.png
YafYonghushouce/img/annotator-icon-sprite.png
YafYonghushouce/img/apple-touch-icon.png
YafYonghushouce/img/cancelfullscreen.png
YafYonghushouce/img/close.png
YafYonghushouce/img/fullscreen.png
YafYonghushouce/img/loader.gif
YafYonghushouce/img/menu-icon.png
YafYonghushouce/img/save.png
YafYonghushouce/img/saved.png
YafYonghushouce/img/settings-s.png
YafYonghushouce/img/settings.png
YafYonghushouce/img/star.png
YafYonghushouce/js/__init__.py
YafYonghushouce/js/epub.js
YafYonghushouce/js/epub.min.js
YafYonghushouce/js/epub.min.map
YafYonghushouce/js/hooks.min.js
YafYonghushouce/js/hooks.min.map
YafYonghushouce/js/reader.js
YafYonghushouce/js/reader.js.map
YafYonghushouce/js/reader.min.js
YafYonghushouce/js/reader.min.map
YafYonghushouce/js/hooks/__init__.py
YafYonghushouce/js/hooks/extensions/__init__.py
YafYonghushouce/js/hooks/extensions/highlight.js
YafYonghushouce/js/libs/__init__.py
YafYonghushouce/js/libs/jquery.min.js
YafYonghushouce/js/libs/localforage.min.js
YafYonghushouce/js/libs/screenfull.js
YafYonghushouce/js/libs/screenfull.min.js
YafYonghushouce/js/libs/zip.min.js
YafYonghushouce/js/plugins/__init__.py
YafYonghushouce/js/plugins/hypothesis.js
YafYonghushouce/js/plugins/search.js
yaf_yonghushouce-2024.3.2.0.dist-info/METADATA
yaf_yonghushouce-2024.3.2.0.dist-info/WHEEL
yaf_yonghushouce-2024.3.2.0.dist-info/entry_points.txt
yaf_yonghushouce-2024.3.2.0.dist-info/top_level.txt
yaf_yonghushouce-2024.3.2.0.dist-info/RECORD
